LICENSE
MANIFEST.in
README.md
setup.py
libryanpythonpro/__init__.py
libryanpythonpro/github_api.py
libryanpythonpro.egg-info/PKG-INFO
libryanpythonpro.egg-info/SOURCES.txt
libryanpythonpro.egg-info/dependency_links.txt
libryanpythonpro.egg-info/not-zip-safe
libryanpythonpro.egg-info/requires.txt
libryanpythonpro.egg-info/top_level.txt